btatt/__init__.py
btatt/att.py
btatt/client.py
btatt/replay.py
btatt/server.py
btatt/pytransform/__init__.py
btatt/pytransform/platforms/linux/aarch64/_pytransform.so
btatt/pytransform/platforms/linux/x86_64/_pytransform.so
btatt-0.0.19.dist-info/LICENSE.txt
btatt-0.0.19.dist-info/METADATA
btatt-0.0.19.dist-info/WHEEL
btatt-0.0.19.dist-info/top_level.txt
btatt-0.0.19.dist-info/RECORD
